quickfin.py
quickfin-1.15.0.dist-info/WHEEL
quickfin-1.15.0.dist-info/METADATA
quickfin-1.15.0.dist-info/RECORD
