Metadata-Version: 2.1
Name: quickfin
Version: 1.15.0
Summary: A Python module providing instant access to live and historical stock market price data, automated Plotly data visualization generators and a metadata catalog for referencing equities, stock symbols, sectors, and industry information.
Author: Derek Evans
Requires-Python: >=3.11
Classifier: Programming Language :: Python :: 3
Classifier: License :: OSI Approved :: MIT License
Classifier: Operating System :: OS Independent
Requires-Dist: plotly
Requires-Dist: streamlit
Project-URL: Changelog, https://quickfin.techbyderek.com/main/changelog.html
Project-URL: Data, https://gist.githubusercontent.com/REPNOT/6bffda0dd727d63a0bd727d4ff1c890a/raw/ec1ea323068b45739ddd595dfab897cc5f7c6487/fin_data.json
Project-URL: Examples, https://quickfin.techbyderek.com/main/examples.html
Project-URL: Home, https://quickfin.techbyderek.com/
Project-URL: Repo, https://github.com/REPNOT/quickfin
